README.md
point_on_earth.py
setup.py
point_on_earth.egg-info/PKG-INFO
point_on_earth.egg-info/SOURCES.txt
point_on_earth.egg-info/dependency_links.txt
point_on_earth.egg-info/requires.txt
point_on_earth.egg-info/top_level.txt