Metadata-Version: 2.1
Name: point-on-earth
Version: 0.0.1
Summary: Generate a geo point on land.
Home-page: https://github.com/alekzvik/point-on-earth/
Author: Alex Vykaliuk
Author-email: alekzvik@gmail.com
License: LICENSE
Keywords: shapely helpers geojson
Platform: UNKNOWN
Classifier: Development Status :: 3 - Alpha
Classifier: Intended Audience :: Developers
Classifier: Topic :: Scientific/Engineering :: GIS
Classifier: License :: OSI Approved :: MIT License
Classifier: Programming Language :: Python :: 3
Classifier: Programming Language :: Python :: 3.4
Classifier: Programming Language :: Python :: 3.5
Classifier: Programming Language :: Python :: 3.6
Provides-Extra: tests
